{"input parameters": ["12", "0", "700", "X", "700_700", "no_Lagrangian"], "instance": {"facilities": 700, "customers": 700}, "times": {"total_time in s": 3841.31, "initialisation_time in s": 1804.64, "node_selection_time in s": 0.01, "implied_demands_time in s": 1559.91, "bounds_time in s": 22.33, "variable_selection in s": 341.4, "greedy_heuristics_time in s": 108.69, "other_time in s": 4.33}, "nodes": {"total": 9, "pruned": 0, "infeasible": 0, "finished": 0}, "solution": {"LB": 6654.465, "UB": 10933.3869, "gap in %": 39.14, "incumbent": [12, 15, 26, 29, 56, 62, 75, 77, 81, 106, 131, 139, 164, 176, 187, 201, 227, 281, 304, 367, 374, 377, 410, 411, 435, 450, 483, 489, 494, 531, 585, 588, 626, 633, 634, 645, 650, 668, 695], "memory in MB": 675.09}, "bounds": {"lower_bounds": [[6654.465, 1804.64]], "upper_bounds": [[11338.313556518362, 1804.64]]}}