{
    "input parameters": [
        "4",
        "1",
        "cap",
        "c",
        "75_100",
        "preprocessing"
    ],
    "instance": {
        "facilities": 75,
        "customers": 100
    },
    "times": {
        "total_time in s": 3600.09,
        "model_building_time in s": 1.28,
        "model_solving_time in s": 3598.81
    },
    "nodes": {
        "total": 10202.0
    },
    "solution": {
        "LB": 1760485.7886,
        "UB": 1938121.9224,
        "gap in %": 0.09,
        "incumbent": [
            13,
            14,
            19,
            27,
            34,
            35,
            48,
            50,
            57,
            58,
            60,
            63,
            71
        ],
        "memory in MB": 581.7
    },
    "bounds": {
        "lower_bounds": [
            [
                0.0,
                0.5892679691314697
            ],
            [
                1362065.4000278916,
                1.3120830059051514
            ],
            [
                1423823.5519701857,
                4.272052049636841
            ],
            [
                1425508.694247535,
                5.28000807762146
            ],
            [
                1425800.4465776088,
                5.427829027175903
            ],
            [
                1425815.2984425186,
                5.645247936248779
            ],
            [
                1473080.4927141166,
                7.760641098022461
            ],
            [
                1473989.7747207128,
                8.175457954406738
            ],
            [
                1474233.404838079,
                8.272743940353394
            ],
            [
                1474293.7667718043,
                8.307245016098022
            ],
            [
                1474298.8868118846,
                8.335020065307617
            ],
            [
                1485875.1760161808,
                10.376743078231812
            ],
            [
                1486320.9087605327,
                10.620896100997925
            ],
            [
                1486381.2889945384,
                10.766982078552246
            ],
            [
                1486387.5350691373,
                10.79521894454956
            ],
            [
                1489841.168058841,
                12.144958972930908
            ],
            [
                1490406.9375301176,
                12.33039402961731
            ],
            [
                1490472.6955733658,
                12.370553016662598
            ],
            [
                1490482.5038183576,
                12.400604009628296
            ],
            [
                1491311.9829742773,
                13.167772054672241
            ],
            [
                1491379.3078404842,
                13.348747968673706
            ],
            [
                1491392.0422281995,
                13.383388996124268
            ],
            [
                1491491.500975723,
                13.960541009902954
            ],
            [
                1491500.1867688794,
                14.130649089813232
            ],
            [
                1491504.6725189025,
                14.598694086074829
            ],
            [
                1491509.1494253508,
                14.75128698348999
            ],
            [
                1491509.4387713885,
                15.180102109909058
            ],
            [
                1491552.5539623885,
                15.572987079620361
            ],
            [
                1491554.1071699464,
                16.89651894569397
            ],
            [
                1491561.7307594267,
                19.48088312149048
            ],
            [
                1499089.3342609855,
                19.91900110244751
            ],
            [
                1499316.6998026294,
                21.348922967910767
            ],
            [
                1506982.0628640766,
                23.132106065750122
            ],
            [
                1510335.8356962588,
                23.82880997657776
            ],
            [
                1519556.6110442693,
                24.92789101600647
            ],
            [
                1533459.41236071,
                25.660094022750854
            ],
            [
                1541125.4572147192,
                26.613327026367188
            ],
            [
                1541127.1599147818,
                34.74387001991272
            ],
            [
                1546130.4346992273,
                45.75794005393982
            ],
            [
                1555197.6334639005,
                50.742801904678345
            ],
            [
                1559063.8754226961,
                64.55364608764648
            ],
            [
                1562871.7499678282,
                72.22924900054932
            ],
            [
                1563751.3495965574,
                80.75528597831726
            ],
            [
                1563790.9896275576,
                83.84353709220886
            ],
            [
                1566496.3783439621,
                91.19977903366089
            ],
            [
                1566530.4485484909,
                95.80341601371765
            ],
            [
                1566543.6519265336,
                196.23255491256714
            ],
            [
                1566690.8600651901,
                208.99377393722534
            ],
            [
                1567175.6053579543,
                210.98116493225098
            ],
            [
                1570689.073217127,
                216.74609303474426
            ],
            [
                1577383.814163611,
                222.62376999855042
            ],
            [
                1585221.9389437567,
                355.9215121269226
            ],
            [
                1594382.3795133529,
                422.47099804878235
            ],
            [
                1616517.5777845008,
                429.16218400001526
            ],
            [
                1616978.6479122376,
                512.2612099647522
            ],
            [
                1626773.6214849208,
                555.7225430011749
            ],
            [
                1628229.3228223466,
                559.0225150585175
            ],
            [
                1630213.324761441,
                600.7072660923004
            ],
            [
                1631568.022604346,
                638.9923629760742
            ],
            [
                1634419.3659633405,
                691.0627629756927
            ],
            [
                1635091.1642890752,
                779.4579679965973
            ],
            [
                1637646.2757553011,
                788.8755531311035
            ],
            [
                1638715.3327366037,
                801.4348380565643
            ],
            [
                1642641.7324176333,
                825.3702449798584
            ],
            [
                1643086.2759642415,
                835.8434839248657
            ],
            [
                1646015.3476760446,
                861.2452259063721
            ],
            [
                1646156.716397618,
                890.0766940116882
            ],
            [
                1646201.0877604808,
                897.3407959938049
            ],
            [
                1646517.5014949525,
                903.5808930397034
            ],
            [
                1649983.5702250313,
                914.6381969451904
            ],
            [
                1650224.6378856895,
                934.1032841205597
            ],
            [
                1651992.737796796,
                949.526025056839
            ],
            [
                1652599.085304445,
                958.2578659057617
            ],
            [
                1653803.794227222,
                997.2294969558716
            ],
            [
                1653883.9855388983,
                1005.5091440677643
            ],
            [
                1654139.776013947,
                1005.9267270565033
            ],
            [
                1655613.2997966486,
                1013.2679960727692
            ],
            [
                1660428.6691378134,
                1046.9995589256287
            ],
            [
                1661560.7208791892,
                1058.890172958374
            ],
            [
                1665336.0611948909,
                1067.535705089569
            ],
            [
                1667249.8650583143,
                1076.4587330818176
            ],
            [
                1667759.3628650156,
                1099.2628691196442
            ],
            [
                1670037.9423756045,
                1103.5149540901184
            ],
            [
                1670111.0071390357,
                1110.5947170257568
            ],
            [
                1671122.6141211668,
                1123.1714141368866
            ],
            [
                1671205.2802133798,
                1140.4149250984192
            ],
            [
                1672585.7392051427,
                1143.919692993164
            ],
            [
                1673385.1680472041,
                1161.6729640960693
            ],
            [
                1677417.406225173,
                1165.3913180828094
            ],
            [
                1677896.3073081262,
                1171.202171087265
            ],
            [
                1678055.9686498062,
                1190.1808750629425
            ],
            [
                1678762.3538625345,
                1209.513128042221
            ],
            [
                1680707.4188456452,
                1224.3693709373474
            ],
            [
                1681239.6473950674,
                1228.695776939392
            ],
            [
                1681353.4578384156,
                1231.0927591323853
            ],
            [
                1681482.9595983773,
                1242.9476039409637
            ],
            [
                1681527.5222222917,
                1252.43532204628
            ],
            [
                1681690.5241043838,
                1260.9012849330902
            ],
            [
                1681845.767296387,
                1263.6817750930786
            ],
            [
                1682279.9796190949,
                1270.8269300460815
            ],
            [
                1683097.873246241,
                1304.6887130737305
            ],
            [
                1683291.4727310266,
                1308.003739118576
            ],
            [
                1683370.5216431387,
                1321.0014090538025
            ],
            [
                1683826.3698026827,
                1343.2494099140167
            ],
            [
                1684747.9222692496,
                1362.68607711792
            ],
            [
                1686303.1726433318,
                1369.653002023697
            ],
            [
                1686455.8870639757,
                1386.013561964035
            ],
            [
                1686487.0037137503,
                1400.5185930728912
            ],
            [
                1686567.256433128,
                1404.9701681137085
            ],
            [
                1686844.751636109,
                1409.9546029567719
            ],
            [
                1687718.59227199,
                1415.9041340351105
            ],
            [
                1688028.4773672807,
                1421.5344049930573
            ],
            [
                1689138.7893150763,
                1428.8871879577637
            ],
            [
                1689424.2854948426,
                1448.1394460201263
            ],
            [
                1689719.6393687949,
                1452.9057729244232
            ],
            [
                1689840.5224845938,
                1458.880392074585
            ],
            [
                1690114.070692335,
                1472.8626599311829
            ],
            [
                1690486.1928183038,
                1475.2310559749603
            ],
            [
                1690587.1085979962,
                1487.8539299964905
            ],
            [
                1691324.0069945618,
                1491.2189209461212
            ],
            [
                1691630.0899698304,
                1495.3539209365845
            ],
            [
                1691697.2565531342,
                1515.430830001831
            ],
            [
                1692138.4684305012,
                1524.5909209251404
            ],
            [
                1692228.6725893852,
                1527.8692150115967
            ],
            [
                1692397.210076742,
                1547.4390530586243
            ],
            [
                1692660.538880946,
                1551.4094610214233
            ],
            [
                1694438.71148399,
                1561.5010130405426
            ],
            [
                1694457.4011154622,
                1590.8325281143188
            ],
            [
                1695351.1781788724,
                1596.6389129161835
            ],
            [
                1695743.8592406246,
                1599.0178470611572
            ],
            [
                1696107.5490336933,
                1603.9856100082397
            ],
            [
                1697644.944857774,
                1608.630578994751
            ],
            [
                1698004.8936877917,
                1611.1871180534363
            ],
            [
                1698206.2757160754,
                1616.9439520835876
            ],
            [
                1699521.7705589521,
                1620.5224459171295
            ],
            [
                1699756.3611289952,
                1631.1998879909515
            ],
            [
                1699921.9442435724,
                1653.1656839847565
            ],
            [
                1700612.698590675,
                1673.1948850154877
            ],
            [
                1700907.4474836562,
                1687.283476114273
            ],
            [
                1701141.9446465308,
                1692.929682970047
            ],
            [
                1701477.357896085,
                1707.0035309791565
            ],
            [
                1702339.090652508,
                1723.9554789066315
            ],
            [
                1705887.453766087,
                1727.4187359809875
            ],
            [
                1705934.1635931018,
                1730.8887240886688
            ],
            [
                1707010.1309820744,
                1734.92724609375
            ],
            [
                1707394.6242571622,
                1739.3853869438171
            ],
            [
                1707654.3295482232,
                1758.622260093689
            ],
            [
                1707757.7970128504,
                1768.7251930236816
            ],
            [
                1707791.5231339182,
                1776.6948311328888
            ],
            [
                1707828.2321752051,
                1780.5063071250916
            ],
            [
                1707982.1152564918,
                1786.224697113037
            ],
            [
                1708224.987213963,
                1795.9488990306854
            ],
            [
                1708452.5109560313,
                1797.6582291126251
            ],
            [
                1708535.7913191798,
                1810.7678580284119
            ],
            [
                1708987.752791348,
                1818.05819106102
            ],
            [
                1709429.2730396895,
                1822.7552330493927
            ],
            [
                1709858.2506469134,
                1837.8235881328583
            ],
            [
                1711377.0479190336,
                1844.4014089107513
            ],
            [
                1711700.869195429,
                1848.3947179317474
            ],
            [
                1711798.5501324555,
                1853.0781729221344
            ],
            [
                1711930.7214513435,
                1872.712865114212
            ],
            [
                1712311.4649965898,
                1875.8895421028137
            ],
            [
                1712708.3238599547,
                1882.9827780723572
            ],
            [
                1712894.8187535712,
                1887.112329006195
            ],
            [
                1713348.6480479133,
                1895.9005579948425
            ],
            [
                1713559.1113970617,
                1899.5567469596863
            ],
            [
                1713608.099653545,
                1904.0744960308075
            ],
            [
                1713838.8718992774,
                1906.4961750507355
            ],
            [
                1713965.8566481054,
                1911.1887700557709
            ],
            [
                1714056.391836568,
                1922.07599401474
            ],
            [
                1714161.4756489545,
                1926.1686420440674
            ],
            [
                1714259.8330526063,
                1933.2638719081879
            ],
            [
                1714264.2019746522,
                1941.946193933487
            ],
            [
                1714809.70601513,
                1954.3840510845184
            ],
            [
                1715262.4549418879,
                1959.9517459869385
            ],
            [
                1715287.7064070858,
                1962.5858359336853
            ],
            [
                1715849.3931746213,
                1964.4542789459229
            ],
            [
                1715965.6186429556,
                1972.5076940059662
            ],
            [
                1716195.9893073111,
                1977.1544489860535
            ],
            [
                1716269.2682094446,
                1981.5198149681091
            ],
            [
                1716960.2280103764,
                1982.936043024063
            ],
            [
                1717538.9832885077,
                1988.986722946167
            ],
            [
                1717728.2692203033,
                2005.6289870738983
            ],
            [
                1718675.035244249,
                2008.598484992981
            ],
            [
                1718943.9943385653,
                2016.4406189918518
            ],
            [
                1719179.2224491616,
                2020.083564043045
            ],
            [
                1719285.5980071842,
                2028.033998966217
            ],
            [
                1719289.2005834756,
                2030.7414100170135
            ],
            [
                1719544.3069580991,
                2036.6521430015564
            ],
            [
                1720323.118105513,
                2042.4516270160675
            ],
            [
                1720575.8182153637,
                2056.369626045227
            ],
            [
                1720694.3625972539,
                2060.832263946533
            ],
            [
                1720969.2668356937,
                2073.770364999771
            ],
            [
                1721837.4192483209,
                2079.2535231113434
            ],
            [
                1721920.2660276897,
                2097.4623050689697
            ],
            [
                1722062.486566234,
                2103.750282049179
            ],
            [
                1722805.7515837303,
                2112.8808929920197
            ],
            [
                1722854.7239200303,
                2117.125508069992
            ],
            [
                1722889.208865187,
                2122.5180361270905
            ],
            [
                1723460.144830861,
                2130.0074961185455
            ],
            [
                1724140.114744062,
                2144.9464960098267
            ],
            [
                1724180.4452255394,
                2177.748955011368
            ],
            [
                1724969.8305517589,
                2185.585932970047
            ],
            [
                1724973.6906104435,
                2187.535723924637
            ],
            [
                1725049.3980515597,
                2192.8964829444885
            ],
            [
                1725157.2884875692,
                2195.509630918503
            ],
            [
                1725461.7289770867,
                2199.4622309207916
            ],
            [
                1725465.5492026394,
                2205.1682341098785
            ],
            [
                1725745.0425862614,
                2207.2483880519867
            ],
            [
                1725894.3891535068,
                2208.577533006668
            ],
            [
                1726466.1955119385,
                2211.121565103531
            ],
            [
                1726532.52197888,
                2215.8240399360657
            ],
            [
                1726532.8676568505,
                2220.187465906143
            ],
            [
                1726533.3260843204,
                2224.7922739982605
            ],
            [
                1726581.508697769,
                2233.088639974594
            ],
            [
                1726809.2854669923,
                2236.506814956665
            ],
            [
                1727246.045724779,
                2238.586030960083
            ],
            [
                1727508.1685344516,
                2245.611349105835
            ],
            [
                1727572.445178989,
                2252.2499499320984
            ],
            [
                1728276.9126150825,
                2256.7463879585266
            ],
            [
                1728942.573954321,
                2262.6276609897614
            ],
            [
                1729016.970810854,
                2264.676470041275
            ],
            [
                1729558.7537922033,
                2275.626979112625
            ],
            [
                1729763.4456521894,
                2277.447914123535
            ],
            [
                1729874.885831682,
                2284.448770046234
            ],
            [
                1730066.9733124997,
                2287.7417380809784
            ],
            [
                1730375.100369583,
                2291.7186510562897
            ],
            [
                1730767.4513661969,
                2304.074336051941
            ],
            [
                1730813.095741654,
                2306.4917600154877
            ],
            [
                1730867.3485927077,
                2309.0172510147095
            ],
            [
                1730978.9567474222,
                2325.7234349250793
            ],
            [
                1731237.1917796652,
                2333.8077290058136
            ],
            [
                1731422.6850896066,
                2339.250692129135
            ],
            [
                1731433.5517245007,
                2344.9110810756683
            ],
            [
                1732035.3697675765,
                2355.0689821243286
            ],
            [
                1732155.5137096373,
                2363.5210099220276
            ],
            [
                1732268.470331778,
                2366.9663610458374
            ],
            [
                1733430.5387465174,
                2370.2358651161194
            ],
            [
                1733457.7133015923,
                2374.2225189208984
            ],
            [
                1733713.6755076947,
                2378.06920003891
            ],
            [
                1733861.0547765826,
                2385.8204119205475
            ],
            [
                1734047.4928090954,
                2390.0785069465637
            ],
            [
                1734171.4813844971,
                2391.3305220603943
            ],
            [
                1734495.7646070446,
                2393.7906260490417
            ],
            [
                1734851.972957015,
                2396.830065011978
            ],
            [
                1734890.3367672176,
                2402.276577949524
            ],
            [
                1734919.2278017537,
                2410.3489139080048
            ],
            [
                1735512.937177064,
                2412.492751121521
            ],
            [
                1735775.0614351968,
                2423.08282995224
            ],
            [
                1735792.0830374938,
                2426.3300290107727
            ],
            [
                1735872.6464100922,
                2449.0088539123535
            ],
            [
                1736282.7750646386,
                2450.337165117264
            ],
            [
                1736283.7523348655,
                2452.6554799079895
            ],
            [
                1736692.279075902,
                2454.612559080124
            ],
            [
                1736705.4297371793,
                2466.2160301208496
            ],
            [
                1736716.403018189,
                2468.333864927292
            ],
            [
                1736828.1503120838,
                2472.3136870861053
            ],
            [
                1737288.861500481,
                2476.217903137207
            ],
            [
                1737369.3747699556,
                2481.333547115326
            ],
            [
                1737551.252861538,
                2489.126352071762
            ],
            [
                1737668.229797112,
                2492.0329060554504
            ],
            [
                1737995.646390423,
                2494.1328411102295
            ],
            [
                1738212.9037665804,
                2497.763792991638
            ],
            [
                1738372.689882611,
                2500.5009570121765
            ],
            [
                1738425.584670218,
                2502.701805114746
            ],
            [
                1738435.5736094236,
                2503.975172996521
            ],
            [
                1738523.2036879214,
                2506.183296918869
            ],
            [
                1738554.7556937635,
                2509.7992799282074
            ],
            [
                1738634.5965478115,
                2510.9531710147858
            ],
            [
                1738773.3937263843,
                2516.7224390506744
            ],
            [
                1739021.3121322005,
                2518.526999950409
            ],
            [
                1739045.8706276347,
                2520.8412430286407
            ],
            [
                1739105.286483992,
                2524.6705729961395
            ],
            [
                1739961.3572846977,
                2536.9638299942017
            ],
            [
                1740467.1759409462,
                2541.3206839561462
            ],
            [
                1740867.2543612593,
                2545.049232006073
            ],
            [
                1740870.5760205772,
                2548.9011731147766
            ],
            [
                1740981.1065044303,
                2550.128921031952
            ],
            [
                1741002.7525961383,
                2551.7200949192047
            ],
            [
                1741160.0804210736,
                2555.345456123352
            ],
            [
                1741277.6806426516,
                2564.958475112915
            ],
            [
                1741277.9668102614,
                2570.0253551006317
            ],
            [
                1741346.0565124815,
                2577.923360109329
            ],
            [
                1741419.224563634,
                2583.2436079978943
            ],
            [
                1741693.2868427304,
                2592.0346529483795
            ],
            [
                1741780.6339953523,
                2594.5308389663696
            ],
            [
                1742169.8194642256,
                2599.025479078293
            ],
            [
                1742272.1775699002,
                2599.476788043976
            ],
            [
                1742696.525443925,
                2601.959042072296
            ],
            [
                1742717.3688837963,
                2605.0478501319885
            ],
            [
                1742978.375953888,
                2620.6825120449066
            ],
            [
                1743315.5295531135,
                2623.8542289733887
            ],
            [
                1743409.7281536078,
                2626.318216085434
            ],
            [
                1743416.6293073108,
                2632.682848930359
            ],
            [
                1743426.3227519663,
                2640.091562986374
            ],
            [
                1743451.4828971927,
                2641.423254966736
            ],
            [
                1743461.7525190725,
                2642.8267951011658
            ],
            [
                1743692.0058115611,
                2644.7763419151306
            ],
            [
                1743920.8865516917,
                2646.794100999832
            ],
            [
                1743984.0031299766,
                2649.547693014145
            ],
            [
                1744069.1901208253,
                2651.625128030777
            ],
            [
                1744155.0840495974,
                2653.9208509922028
            ],
            [
                1744587.6278888057,
                2657.822478055954
            ],
            [
                1744733.5770081289,
                2672.5729360580444
            ],
            [
                1744792.0794171614,
                2677.2497169971466
            ],
            [
                1745503.478011484,
                2680.2450139522552
            ],
            [
                1745779.0929988024,
                2682.6166520118713
            ],
            [
                1746030.5624500082,
                2686.331265926361
            ],
            [
                1746117.5866900894,
                2690.11580491066
            ],
            [
                1746126.342676913,
                2701.515202999115
            ],
            [
                1746190.0387143672,
                2702.494486093521
            ],
            [
                1746289.207251187,
                2705.464868068695
            ],
            [
                1746350.4011856378,
                2716.0872769355774
            ],
            [
                1746463.2917726801,
                2729.8464999198914
            ],
            [
                1746800.5016061724,
                2732.476119995117
            ],
            [
                1747265.323196653,
                2737.208647966385
            ],
            [
                1747388.863300553,
                2743.7199280261993
            ],
            [
                1747498.7138591013,
                2748.304801940918
            ],
            [
                1747538.3111051684,
                2749.6522419452667
            ],
            [
                1747596.6781487768,
                2760.7256829738617
            ],
            [
                1748067.9828599056,
                2772.2954070568085
            ],
            [
                1748090.6782066277,
                2774.7839980125427
            ],
            [
                1748200.2025753823,
                2779.655702114105
            ],
            [
                1748209.7947225042,
                2788.7525219917297
            ],
            [
                1748568.3805985407,
                2790.9883449077606
            ],
            [
                1748747.281410626,
                2798.2561960220337
            ],
            [
                1749009.5940539404,
                2801.0160241127014
            ],
            [
                1749108.2924648647,
                2802.8629660606384
            ],
            [
                1749531.5480035022,
                2804.3238639831543
            ],
            [
                1749644.7678776584,
                2806.367660999298
            ],
            [
                1750152.963364527,
                2808.717633008957
            ],
            [
                1750155.4598180787,
                2813.6805119514465
            ],
            [
                1750415.1994480572,
                2816.2612669467926
            ],
            [
                1750492.4976059927,
                2818.257241010666
            ],
            [
                1750508.8956186222,
                2820.565439939499
            ],
            [
                1750515.8083742838,
                2823.812556028366
            ],
            [
                1750822.7864409597,
                2824.577264070511
            ],
            [
                1751283.5056583437,
                2826.260227918625
            ],
            [
                1751633.1081519786,
                2828.1979739665985
            ],
            [
                1751731.5414695656,
                2830.5207080841064
            ],
            [
                1751737.354457148,
                2832.829313993454
            ],
            [
                1751834.7141393,
                2834.153244972229
            ],
            [
                1751991.8345124878,
                2837.972216129303
            ],
            [
                1752161.6637602712,
                2846.909898996353
            ],
            [
                1752364.0556248145,
                2851.4793050289154
            ],
            [
                1752624.203879949,
                2858.267669916153
            ],
            [
                1753071.5390322725,
                2862.7023940086365
            ],
            [
                1753410.7938276005,
                2864.9695160388947
            ],
            [
                1753425.2507973048,
                2871.096846103668
            ],
            [
                1753511.3772730166,
                2874.050760984421
            ],
            [
                1753599.0932146613,
                2884.182879924774
            ],
            [
                1753645.6373175748,
                2893.331687927246
            ],
            [
                1753681.2637418834,
                2895.0755739212036
            ],
            [
                1753785.4483003893,
                2900.2679290771484
            ],
            [
                1753936.3100583698,
                2904.0744030475616
            ],
            [
                1754018.7896619574,
                2905.274039030075
            ],
            [
                1754027.884407035,
                2907.5832030773163
            ],
            [
                1754043.0103818823,
                2909.153810977936
            ],
            [
                1754090.5582325398,
                2913.1557099819183
            ],
            [
                1754102.7338538605,
                2915.407289981842
            ],
            [
                1754231.936284368,
                2921.348084926605
            ],
            [
                1754280.89589719,
                2925.3923420906067
            ],
            [
                1754298.7656560119,
                2933.4743840694427
            ],
            [
                1754580.0554194073,
                2935.073436975479
            ],
            [
                1754580.7755775314,
                2937.3363819122314
            ],
            [
                1754775.6604278337,
                2940.502511024475
            ],
            [
                1754893.4056855016,
                2949.624843120575
            ],
            [
                1754978.7726338098,
                2951.2218890190125
            ],
            [
                1754981.3381715044,
                2956.939798116684
            ],
            [
                1755421.9970958189,
                2959.7058520317078
            ],
            [
                1755469.1926582253,
                2961.644921064377
            ],
            [
                1755535.4195494698,
                2963.5846030712128
            ],
            [
                1755598.1452911405,
                2968.12668800354
            ],
            [
                1755638.8982666137,
                2970.6571640968323
            ],
            [
                1755671.0812718065,
                2972.35551905632
            ],
            [
                1755690.5303513529,
                2972.967665910721
            ],
            [
                1755839.7089689996,
                2974.3765869140625
            ],
            [
                1756028.130978055,
                2978.2337729930878
            ],
            [
                1756045.7010385143,
                2980.5786340236664
            ],
            [
                1756057.0616746922,
                2981.7082149982452
            ],
            [
                1756093.5582911293,
                2983.9391820430756
            ],
            [
                1756285.8770244936,
                2990.7646210193634
            ],
            [
                1756464.6344909505,
                2995.3797829151154
            ],
            [
                1757012.2544729728,
                3002.3637840747833
            ],
            [
                1757013.090331164,
                3005.487860918045
            ],
            [
                1757105.497971881,
                3009.430135011673
            ],
            [
                1757321.461947848,
                3011.549966096878
            ],
            [
                1757341.8008400043,
                3019.1269171237946
            ],
            [
                1757597.4778750567,
                3026.837007045746
            ],
            [
                1757633.564463285,
                3027.909639120102
            ],
            [
                1757703.0840618403,
                3029.9354519844055
            ],
            [
                1757772.164167112,
                3032.269730091095
            ],
            [
                1757811.2959912668,
                3042.4723269939423
            ],
            [
                1757908.5612683273,
                3051.279484987259
            ],
            [
                1757917.928981366,
                3054.0746409893036
            ],
            [
                1758023.7079851602,
                3063.7529571056366
            ],
            [
                1758063.8689658428,
                3070.0940499305725
            ],
            [
                1758134.0956501376,
                3074.695743083954
            ],
            [
                1758142.903280132,
                3078.8085601329803
            ],
            [
                1758193.5744079058,
                3093.1642410755157
            ],
            [
                1758315.9206257914,
                3099.2433409690857
            ],
            [
                1758419.5055180076,
                3102.2942700386047
            ],
            [
                1758421.5586741888,
                3106.8572959899902
            ],
            [
                1758433.1489504112,
                3111.0778720378876
            ],
            [
                1759188.357478617,
                3113.409548997879
            ],
            [
                1759191.9256454126,
                3115.23193693161
            ],
            [
                1759283.0817060042,
                3124.382777929306
            ],
            [
                1759302.3513236889,
                3126.38427400589
            ],
            [
                1759415.4645537608,
                3128.597636938095
            ],
            [
                1759603.0385453461,
                3138.197991132736
            ],
            [
                1759631.4542678883,
                3140.891086101532
            ],
            [
                1759649.1693120694,
                3143.2627789974213
            ],
            [
                1759693.1924047815,
                3145.851303100586
            ],
            [
                1759709.2325198036,
                3153.957118988037
            ],
            [
                1759885.240809721,
                3167.1099910736084
            ],
            [
                1759994.753758365,
                3172.163202047348
            ],
            [
                1760175.8868412736,
                3174.5132579803467
            ],
            [
                1760198.1189843416,
                3179.599363088608
            ],
            [
                1760282.1919605657,
                3182.376496076584
            ],
            [
                1760309.3540286697,
                3187.5641090869904
            ],
            [
                1760480.1910054085,
                3190.4180879592896
            ],
            [
                1760485.7886422027,
                3192.3476750850677
            ]
        ],
        "upper_bounds": [
            [
                3051323.3814499998,
                0.6488749980926514
            ],
            [
                2145263.21238,
                1.5782649517059326
            ],
            [
                2132342.80675,
                12.16977596282959
            ],
            [
                2050614.52553,
                14.105515003204346
            ],
            [
                2026462.0832599998,
                29.920604944229126
            ],
            [
                1971135.8700499998,
                33.9717230796814
            ],
            [
                1955025.6158099999,
                46.09953713417053
            ],
            [
                1938121.92245,
                471.3421449661255
            ]
        ]
    }
}